sqrc/__init__.py
sqrc-0.0.3.data/data/LICENSE
sqrc-0.0.3.data/data/README.md
sqrc-0.0.3.dist-info/LICENSE
sqrc-0.0.3.dist-info/METADATA
sqrc-0.0.3.dist-info/WHEEL
sqrc-0.0.3.dist-info/entry_points.txt
sqrc-0.0.3.dist-info/top_level.txt
sqrc-0.0.3.dist-info/RECORD
