Metadata-Version: 2.1
Name: sqrc
Version: 0.0.3
Summary: SQRC (show QR code) is simple utility that takes data from the clipboard and shows you QR code.
Home-page: https://github.com/koutoftimer/sqrc
Author: Ruslan Kovtun
Author-email: koutoftimer@gmail.com
License: GPLv3
Platform: UNKNOWN
Classifier: Development Status :: 3 - Alpha
Classifier: Environment :: Console
Classifier: Intended Audience :: End Users/Desktop
Classifier: License :: OSI Approved :: GNU General Public License v3 (GPLv3)
Classifier: Operating System :: OS Independent
Classifier: Programming Language :: Python :: 2
Classifier: Programming Language :: Python :: 2.7
Classifier: Programming Language :: Python :: 3
Classifier: Programming Language :: Python :: 3.5
Classifier: Programming Language :: Python :: 3.6
Classifier: Topic :: Multimedia :: Graphics
Classifier: Topic :: Utilities
Requires-Dist: pyperclip (==1.7.0)
Requires-Dist: qrcode[pil] (==6.1)
